automatize/README.md
automatize/__init__.py
automatize/analysis.py
automatize/app.py
automatize/automatize-web
automatize/generator.py
automatize/graphics.py
automatize/main.py
automatize/movelets.py
automatize/optionals.txt
automatize/preprocessing.py
automatize/pyproject.toml
automatize/requirements.txt
automatize/results.py
automatize/run.py
automatize/script.py
automatize/setup.py
automatize/assets/__init__.py
automatize/assets/app_base.py
automatize/assets/appstyle.css
automatize/assets/citation.bib
automatize/assets/config.py
automatize/assets/experimental_history.csv
automatize/assets/favicon.ico
automatize/assets/mat.svg
automatize/assets/examples/Automatize_Sample_Code.html
automatize/assets/examples/Automatize_Sample_Code.ipynb
automatize/assets/examples/Foursquare_Example.csv
automatize/assets/examples/__init__.py
automatize/assets/examples/Example/__init__.py
automatize/assets/examples/Example/data/Descriptor.json
automatize/assets/examples/Example/data/Descriptor_hp.json
automatize/assets/examples/Example/data/__init__.py
automatize/assets/examples/Example/data/test.csv
automatize/assets/examples/Example/data/test.mat
automatize/assets/examples/Example/data/test.zip
automatize/assets/examples/Example/data/train.csv
automatize/assets/examples/Example/data/train.mat
automatize/assets/examples/Example/data/train.zip
automatize/assets/examples/css/__init__.py
automatize/assets/examples/css/colorful.css
automatize/assets/examples/css/notebook.css
automatize/assets/method/BITULER.md
automatize/assets/method/DeepeST.md
automatize/assets/method/Dodge.md
automatize/assets/method/HIPERMovelets.md
automatize/assets/method/MARC.md
automatize/assets/method/MASTERMovelets.jar
automatize/assets/method/MASTERMovelets.md
automatize/assets/method/Movelets.md
automatize/assets/method/POIF.md
automatize/assets/method/POIS.md
automatize/assets/method/SUPERMovelets.md
automatize/assets/method/TRF.md
automatize/assets/method/TULVAE.md
automatize/assets/method/TXGB.md
automatize-1.0b7.dist-info/LICENSE
automatize-1.0b7.dist-info/METADATA
automatize-1.0b7.dist-info/WHEEL
automatize-1.0b7.dist-info/top_level.txt
automatize-1.0b7.dist-info/RECORD
